django_vite_ssr/__init__.py
django_vite_ssr/core.py
django_vite_ssr/helper.py
django_vite_ssr-0.2.8.dist-info/METADATA
django_vite_ssr-0.2.8.dist-info/WHEEL
django_vite_ssr-0.2.8.dist-info/top_level.txt
django_vite_ssr-0.2.8.dist-info/RECORD
