Metadata-Version: 2.4
Name: django-vite-ssr
Version: 0.2.8
Summary: Django integration for Vite Server-Side Rendering (SSR)
Home-page: https://github.com/lucas-neitzke-ssys/django-vite-ssr
Author: Lucas de Oliveira Neitzke
Author-email: lucas.neitzke@ssys.com.br
Classifier: Development Status :: 3 - Alpha
Classifier: Intended Audience :: Developers
Classifier: License :: OSI Approved :: MIT License
Classifier: Operating System :: OS Independent
Classifier: Programming Language :: Python :: 3
Classifier: Programming Language :: Python :: 3.7
Classifier: Programming Language :: Python :: 3.8
Classifier: Programming Language :: Python :: 3.9
Classifier: Programming Language :: Python :: 3.10
Classifier: Framework :: Django
Classifier: Framework :: Django :: 3.2
Classifier: Framework :: Django :: 4.0
Classifier: Framework :: Django :: 4.1
Requires-Python: >=3.7
Requires-Dist: Django>=3.2
Requires-Dist: beautifulsoup4>=4.9.0
Dynamic: author
Dynamic: author-email
Dynamic: classifier
Dynamic: description
Dynamic: description-content-type
Dynamic: home-page
Dynamic: requires-dist
Dynamic: requires-python
Dynamic: summary
